layoutmargin/__init__.py
layoutmargin/_add_background.py
layoutmargin/_margin_layout.py
layoutmargin-20190911.dist-info/LICENSE
layoutmargin-20190911.dist-info/METADATA
layoutmargin-20190911.dist-info/WHEEL
layoutmargin-20190911.dist-info/top_level.txt
layoutmargin-20190911.dist-info/RECORD
