Metadata-Version: 2.1
Name: layoutmargin
Version: 20190911
Summary: Mixins that adds margin functionality to Kivy widgets
Home-page: https://github.com/AndreMiras/garden.layoutmargin
Author: Andre Miras
License: UNKNOWN
Platform: UNKNOWN
Requires-Dist: kivy
